[
  {
    "id": "recipe-kimchi-jjim",
    "title": "집밥 김치찜",
    "subtitle": "푹 익은 김치와 돼지고기로 완성하는 밥도둑 메뉴",
    "category": "찜/조림",
    "description": "새콤한 김치와 부드러운 고기를 푹 졸여내 깊은 맛이 나는 대표 집밥입니다.",
    "servings": "2~3인분",
    "cookTime": "약 45분",
    "spicyLevel": "중",
    "image": "/images/kimchi-jjim.svg",
    "ingredients": [
      "돼지고기 목살 600g",
      "잘 익은 김치 1/4포기",
      "양파 1개",
      "대파 1대",
      "다진 마늘 1큰술",
      "고춧가루 1큰술",
      "물 또는 육수 500ml"
    ],
    "steps": [
      "냄비 바닥에 김치를 깔고 고기를 올립니다.",
      "양념 재료와 물을 넣고 중약불에서 35분간 끓입니다.",
      "뚜껑을 열고 국물을 졸여 진하게 마무리합니다."
    ],
    "tip": "묵은지를 쓰면 더 진한 맛이 납니다.",
    "updatedAt": "2026-03-31T09:00:00.000Z"
  },
  {
    "id": "recipe-doenjang-jjigae",
    "title": "구수한 된장찌개",
    "subtitle": "두부와 애호박이 어우러진 매일 먹는 집된장 맛",
    "category": "찌개",
    "description": "멸치육수에 된장을 풀어 구수하면서도 깔끔하게 즐기는 찌개입니다.",
    "servings": "2인분",
    "cookTime": "약 25분",
    "spicyLevel": "하",
    "image": "/images/doenjang-jjigae.svg",
    "ingredients": [
      "된장 2큰술",
      "두부 1/2모",
      "애호박 1/3개",
      "양파 1/2개",
      "청양고추 1개",
      "멸치육수 500ml"
    ],
    "steps": [
      "육수에 된장을 잘 풀어 끓입니다.",
      "호박, 양파, 두부를 넣고 10분간 더 끓입니다.",
      "청양고추를 넣고 한소끔 끓여 마무리합니다."
    ],
    "tip": "감자 한 조각을 넣으면 국물이 더 진해집니다.",
    "updatedAt": "2026-03-31T08:50:00.000Z"
  },
  {
    "id": "recipe-jeyuk-bokkeum",
    "title": "매콤 제육볶음",
    "subtitle": "고추장 양념으로 빠르게 볶아내는 든든한 한 접시",
    "category": "볶음",
    "description": "불향 가득한 매콤달콤 제육볶음으로 상추쌈까지 완벽한 메뉴입니다.",
    "servings": "2~3인분",
    "cookTime": "약 30분",
    "spicyLevel": "상",
    "image": "/images/jeyuk-bokkeum.svg",
    "ingredients": [
      "돼지고기 앞다리살 500g",
      "고추장 2큰술",
      "고춧가루 1큰술",
      "간장 1큰술",
      "양파 1개",
      "대파 1대"
    ],
    "steps": [
      "고기에 양념을 넣어 10분간 재웁니다.",
      "센 불에 양파와 함께 빠르게 볶습니다.",
      "대파를 넣고 불향 나게 마무리합니다."
    ],
    "tip": "마지막에 참기름을 한 방울 넣으면 향이 좋아집니다.",
    "updatedAt": "2026-03-31T08:40:00.000Z"
  },
  {
    "id": "recipe-bulgogi",
    "title": "달큰한 소불고기",
    "subtitle": "간장 양념으로 아이도 좋아하는 부드러운 메인 메뉴",
    "category": "고기요리",
    "description": "배즙 없이도 달큰하고 촉촉하게 즐길 수 있는 기본 불고기 레시피입니다.",
    "servings": "3인분",
    "cookTime": "약 25분",
    "spicyLevel": "하",
    "image": "/images/bulgogi.svg",
    "ingredients": [
      "소불고기용 고기 500g",
      "간장 4큰술",
      "설탕 1큰술",
      "양파 1/2개",
      "당근 약간",
      "대파 1대"
    ],
    "steps": [
      "고기에 간장 양념을 넣어 15분간 재웁니다.",
      "채소를 넣고 중불에서 촉촉하게 볶습니다.",
      "국물이 자작해질 때까지 졸여냅니다."
    ],
    "tip": "버섯을 넣으면 감칠맛이 더 살아납니다.",
    "updatedAt": "2026-03-31T08:30:00.000Z"
  },
  {
    "id": "recipe-sundubu-jjigae",
    "title": "얼큰 순두부찌개",
    "subtitle": "보들보들 순두부와 달걀이 어울리는 뜨끈한 한 그릇",
    "category": "찌개",
    "description": "짧은 시간에 끓여도 깊은 맛이 살아나는 얼큰한 순두부찌개입니다.",
    "servings": "2인분",
    "cookTime": "약 20분",
    "spicyLevel": "중",
    "image": "/images/sundubu-jjigae.svg",
    "ingredients": [
      "순두부 1봉",
      "고춧가루 1큰술",
      "다진 마늘 1큰술",
      "양파 1/2개",
      "바지락 한 줌",
      "달걀 1개"
    ],
    "steps": [
      "냄비에 기름을 두르고 고춧가루와 마늘을 볶아 향을 냅니다.",
      "양파와 바지락, 물을 넣고 끓입니다.",
      "순두부를 넣고 달걀을 올려 한소끔 끓입니다."
    ],
    "tip": "들기름을 조금 넣으면 고소함이 살아납니다.",
    "updatedAt": "2026-03-31T08:20:00.000Z"
  },
  {
    "id": "recipe-dakbokkeumtang",
    "title": "칼칼 닭볶음탕",
    "subtitle": "감자와 닭고기를 매콤하게 졸여낸 푸짐한 냄비요리",
    "category": "찜/조림",
    "description": "국물까지 맛있는 닭볶음탕으로 가족 식탁의 메인 메뉴로 잘 어울립니다.",
    "servings": "3~4인분",
    "cookTime": "약 50분",
    "spicyLevel": "중",
    "image": "/images/dakbokkeumtang.svg",
    "ingredients": [
      "닭 1마리",
      "감자 2개",
      "양파 1개",
      "고추장 2큰술",
      "간장 3큰술",
      "대파 1대"
    ],
    "steps": [
      "닭을 한번 데쳐 잡내를 제거합니다.",
      "양념과 채소, 물을 넣고 30분 이상 끓입니다.",
      "감자가 익고 국물이 자작해지면 마무리합니다."
    ],
    "tip": "당면을 마지막에 넣으면 더욱 푸짐합니다.",
    "updatedAt": "2026-03-31T08:10:00.000Z"
  },
  {
    "id": "recipe-japchae",
    "title": "잔치 잡채",
    "subtitle": "당면과 채소를 윤기 있게 볶아내는 인기 반찬",
    "category": "반찬",
    "description": "특별한 날은 물론 평일 반찬으로도 좋은 달큰한 잡채입니다.",
    "servings": "3인분",
    "cookTime": "약 35분",
    "spicyLevel": "하",
    "image": "/images/japchae.svg",
    "ingredients": [
      "당면 200g",
      "시금치 한 줌",
      "당근 1/3개",
      "양파 1/2개",
      "간장 3큰술",
      "참기름 1큰술"
    ],
    "steps": [
      "당면을 삶아 찬물에 헹군 뒤 물기를 뺍니다.",
      "채소를 각각 볶아 향을 살립니다.",
      "당면과 채소를 양념에 함께 볶아 마무리합니다."
    ],
    "tip": "당면을 너무 오래 삶지 않으면 식감이 탱탱합니다.",
    "updatedAt": "2026-03-31T08:00:00.000Z"
  },
  {
    "id": "recipe-tteokbokki",
    "title": "국물 떡볶이",
    "subtitle": "쫄깃한 떡과 어묵이 어우러진 매콤달콤 분식 메뉴",
    "category": "분식",
    "description": "아이와 어른 모두 좋아하는 기본 국물 떡볶이 레시피입니다.",
    "servings": "2인분",
    "cookTime": "약 20분",
    "spicyLevel": "중",
    "image": "/images/tteokbokki.svg",
    "ingredients": [
      "떡볶이 떡 300g",
      "어묵 2장",
      "고추장 1.5큰술",
      "설탕 1큰술",
      "대파 1/2대",
      "물 400ml"
    ],
    "steps": [
      "양념을 물에 풀어 끓입니다.",
      "떡과 어묵을 넣고 걸쭉해질 때까지 끓입니다.",
      "대파를 넣고 한 번 더 끓여냅니다."
    ],
    "tip": "삶은 달걀을 곁들이면 더 든든합니다.",
    "updatedAt": "2026-03-31T07:50:00.000Z"
  },
  {
    "id": "recipe-bibimbap",
    "title": "채소 비빔밥",
    "subtitle": "나물과 고추장 양념으로 간단하게 완성하는 한 그릇",
    "category": "한그릇",
    "description": "냉장고 속 반찬을 활용해 손쉽게 만들 수 있는 든든한 비빔밥입니다.",
    "servings": "1~2인분",
    "cookTime": "약 15분",
    "spicyLevel": "중",
    "image": "/images/bibimbap.svg",
    "ingredients": [
      "밥 2공기",
      "시금치나물 약간",
      "콩나물무침 약간",
      "당근채 약간",
      "계란 1개",
      "고추장 1큰술"
    ],
    "steps": [
      "그릇에 밥을 담고 준비한 나물을 올립니다.",
      "계란프라이를 얹고 고추장을 곁들입니다.",
      "참기름을 살짝 넣고 비벼 먹습니다."
    ],
    "tip": "불고기나 참치를 올리면 한 끼 식사로 더 풍성해집니다.",
    "updatedAt": "2026-03-31T07:40:00.000Z"
  },
  {
    "id": "recipe-galbijjim",
    "title": "부드러운 갈비찜",
    "subtitle": "특별한 날 상차림에 잘 어울리는 달짝지근한 메인 요리",
    "category": "특별식",
    "description": "소갈비를 푹 삶아 양념에 졸여내면 손님상에도 잘 어울리는 갈비찜이 완성됩니다.",
    "servings": "3~4인분",
    "cookTime": "약 70분",
    "spicyLevel": "하",
    "image": "/images/galbijjim.svg",
    "ingredients": [
      "소갈비 1kg",
      "간장 5큰술",
      "배즙 또는 사과즙 3큰술",
      "무 1/4개",
      "당근 1/2개",
      "대추 약간"
    ],
    "steps": [
      "갈비를 찬물에 담가 핏물을 빼고 한번 데칩니다.",
      "양념과 물을 넣고 중약불에서 푹 익힙니다.",
      "무와 당근을 넣고 윤기 나게 졸여냅니다."
    ],
    "tip": "전날 미리 만들어두면 양념이 배어 더 맛있습니다.",
    "updatedAt": "2026-03-31T07:30:00.000Z"
  }
]
